skip_types/__init__.py
skip_types/pob/__init__.py
skip_types/pob/builder/__init__.py
skip_types/pob/builder/module/__init__.py
skip_types/pob/builder/module/v1/__init__.py
skip_types/pob/builder/module/v1/module_pb2.py
skip_types/pob/builder/v1/__init__.py
skip_types/pob/builder/v1/genesis_pb2.py
skip_types/pob/builder/v1/query_pb2.py
skip_types/pob/builder/v1/tx_pb2.py
skip_types/sdk/__init__.py
skip_types/sdk/auction/__init__.py
skip_types/sdk/auction/module/__init__.py
skip_types/sdk/auction/module/v1/__init__.py
skip_types/sdk/auction/module/v1/module_pb2.py
skip_types/sdk/auction/v1/__init__.py
skip_types/sdk/auction/v1/genesis_pb2.py
skip_types/sdk/auction/v1/query_pb2.py
skip_types/sdk/auction/v1/tx_pb2.py
skip_utility/__init__.py
skip_utility/tx.py
skip_types-0.1.0.dist-info/LICENCE.txt
skip_types-0.1.0.dist-info/METADATA
skip_types-0.1.0.dist-info/WHEEL
skip_types-0.1.0.dist-info/top_level.txt
skip_types-0.1.0.dist-info/RECORD
